CHANGES.rst
LICENSE.rst
MANIFEST.in
README.rst
setup.cfg
setup.py
tox.ini
docs/Makefile
docs/changes.rst
docs/conf.py
docs/contributing.rst
docs/crash_course.rst
docs/csrf.rst
docs/ext.rst
docs/faq.rst
docs/fields.rst
docs/forms.rst
docs/i18n.rst
docs/index.rst
docs/license.rst
docs/make.bat
docs/meta.rst
docs/requirements.txt
docs/specific_problems.rst
docs/validators.rst
docs/whats_new.rst
docs/widgets.rst
docs/_static/e-wtforms.png
docs/_static/wtforms.png
src/e_WTForms.egg-info/PKG-INFO
src/e_WTForms.egg-info/SOURCES.txt
src/e_WTForms.egg-info/dependency_links.txt
src/e_WTForms.egg-info/requires.txt
src/e_WTForms.egg-info/top_level.txt
src/wtforms/__init__.py
src/wtforms/form.py
src/wtforms/i18n.py
src/wtforms/meta.py
src/wtforms/utils.py
src/wtforms/validators.py
src/wtforms/csrf/__init__.py
src/wtforms/csrf/core.py
src/wtforms/csrf/session.py
src/wtforms/fields/__init__.py
src/wtforms/fields/core.py
src/wtforms/fields/simple.py
src/wtforms/locale/README.md
src/wtforms/locale/wtforms.pot
src/wtforms/locale/ar/LC_MESSAGES/wtforms.mo
src/wtforms/locale/ar/LC_MESSAGES/wtforms.po
src/wtforms/locale/bg/LC_MESSAGES/wtforms.mo
src/wtforms/locale/bg/LC_MESSAGES/wtforms.po
src/wtforms/locale/ca/LC_MESSAGES/wtforms.mo
src/wtforms/locale/ca/LC_MESSAGES/wtforms.po
src/wtforms/locale/cs_CZ/LC_MESSAGES/wtforms.mo
src/wtforms/locale/cs_CZ/LC_MESSAGES/wtforms.po
src/wtforms/locale/cy/LC_MESSAGES/wtforms.mo
src/wtforms/locale/cy/LC_MESSAGES/wtforms.po
src/wtforms/locale/de/LC_MESSAGES/wtforms.mo
src/wtforms/locale/de/LC_MESSAGES/wtforms.po
src/wtforms/locale/de_CH/LC_MESSAGES/wtforms.mo
src/wtforms/locale/de_CH/LC_MESSAGES/wtforms.po
src/wtforms/locale/el/LC_MESSAGES/wtforms.mo
src/wtforms/locale/el/LC_MESSAGES/wtforms.po
src/wtforms/locale/en/LC_MESSAGES/wtforms.mo
src/wtforms/locale/en/LC_MESSAGES/wtforms.po
src/wtforms/locale/es/LC_MESSAGES/wtforms.mo
src/wtforms/locale/es/LC_MESSAGES/wtforms.po
src/wtforms/locale/et/LC_MESSAGES/wtforms.mo
src/wtforms/locale/et/LC_MESSAGES/wtforms.po
src/wtforms/locale/fa/LC_MESSAGES/wtforms.mo
src/wtforms/locale/fa/LC_MESSAGES/wtforms.po
src/wtforms/locale/fi/LC_MESSAGES/wtforms.mo
