Metadata-Version: 2.1
Name: e-WTForms
Version: 0.0.1
Summary: Form validation and rendering for Python web development.
Home-page: https://e-wtforms.readthedocs.io/
Maintainer: ennkua
Maintainer-email: ennkua@gmail.com
License: BSD-3-Clause
Project-URL: Documentation, https://e-wtforms.readthedocs.io/
Project-URL: Code, https://github.com/ennkua/e-wtforms
Project-URL: Issue Tracker, https://github.com/ennkua/e-wtforms/issues
Platform: UNKNOWN
Classifier: Development Status :: 5 - Production/Stable
Classifier: Environment :: Web Environment
Classifier: Intended Audience :: Developers
Classifier: License :: OSI Approved :: BSD License
Classifier: Operating System :: OS Independent
Classifier: Programming Language :: Python
Classifier: Topic :: Internet :: WWW/HTTP :: Dynamic Content
Requires-Python: >=3.6
Provides-Extra: email
